{
    "size": {
        "border": {
            "width": {
                "small": {
                    "value": "0.125"
                },
                "medium": {
                    "value": "0.25"
                },
                "large": {
                    "value": "0.5"
                }
            },
            "radius": {
                "xs": {
                    "value": "0.5"
                },
                "small": {
                    "value": "0.75"
                },
                "medium": {
                    "value": "1"
                },
                "large": {
                    "value": "1.5"
                },
                "xl": {
                    "value": "2"
                },
                "xxl": {
                    "value": "3"
                }
            }
        }
    }
}